gpt/__init__.py
gpt/chat_gpt.py
gpt/whisper.py
nantis_llm_toolbox-0.1.0.dist-info/METADATA
nantis_llm_toolbox-0.1.0.dist-info/WHEEL
nantis_llm_toolbox-0.1.0.dist-info/top_level.txt
nantis_llm_toolbox-0.1.0.dist-info/RECORD
