Metadata-Version: 2.4
Name: nantis_llm_toolbox
Version: 0.1.0
Summary: A package containing my llm tools
Home-page: https://github.com/AbakusNantis/llm-toolbox
Author: Abakus Nantis
Author-email: bastian.knaus@gmail.com
Requires-Python: >=3.10
Dynamic: author
Dynamic: author-email
Dynamic: home-page
Dynamic: requires-python
Dynamic: summary
